langchain_model/__init__.py
langchain_model-0.0.6.dist-info/METADATA
langchain_model-0.0.6.dist-info/WHEEL
langchain_model-0.0.6.dist-info/top_level.txt
langchain_model-0.0.6.dist-info/RECORD
