Metadata-Version: 2.1
Name: langchain-model
Version: 0.0.6
Summary: Populate Pydantic Models with LangChain
Requires-Dist: langchain
Requires-Dist: pydantic (<2)
